{"cameraMode":{"drawMode":0,"name":"Shaded","section":"Shading Mode"},"sceneLighting":true,"audioPlay":false,"sceneViewState":{"m_AlwaysRefresh":false,"showFog":true,"showSkybox":true,"showFlares":true,"showImageEffects":true,"showParticleSystems":true,"showVisualEffectGraphs":true,"m_FxEnabled":true},"in2DMode":false,"pivot":{"x":4.62845516204834,"y":5.18007755279541,"z":-14.203497886657715},"rotation":{"x":-0.31267479062080386,"y":0.17838744819164277,"z":-0.05990837886929512,"w":-0.9310386776924133},"size":2.594367742538452,"orthographic":false}